pyfeyngen/__init__.py
pyfeyngen/errors.py
pyfeyngen/exporter.py
pyfeyngen/layout.py
pyfeyngen/layout_engine.py
pyfeyngen/logger.py
pyfeyngen/parser.py
pyfeyngen/physics.py
pyfeyngen-0.1.1.dist-info/licenses/LICENSE
pyfeyngen-0.1.1.dist-info/METADATA
pyfeyngen-0.1.1.dist-info/WHEEL
pyfeyngen-0.1.1.dist-info/top_level.txt
pyfeyngen-0.1.1.dist-info/RECORD
