Metadata-Version: 2.4
Name: pyfeyngen
Version: 0.1.1
Summary: A Python library to convert particle physics reaction strings into LaTeX TikZ-Feynman diagrams.
Author: Saux Paulhenry & Contributors
License: MIT
Project-URL: Homepage, https://github.com/paulhenry46/pyfeyngen
Project-URL: Bug Tracker, https://github.com/paulhenry46/pyfeyngen/issues
Keywords: feynman,tikz,physics,diagram,latex
Classifier: Programming Language :: Python :: 3
Classifier: License :: OSI Approved :: MIT License
Classifier: Operating System :: OS Independent
Classifier: Intended Audience :: Science/Research
Classifier: Topic :: Scientific/Engineering :: Physics
Requires-Python: >=3.8
License-File: LICENSE
Dynamic: license-file
